si_sr_gan_light/__init__.py
si_sr_gan_light/run.py
si_sr_gan_light/__pycache__/__init__.cpython-310.pyc
si_sr_gan_light/__pycache__/__init__.cpython-38.pyc
si_sr_gan_light/__pycache__/run.cpython-310.pyc
si_sr_gan_light/__pycache__/run.cpython-38.pyc
si_sr_gan_light/models/__init__.py
si_sr_gan_light/models/si_sr_gan_light_5x.onnx
si_sr_gan_light-0.0.0.dist-info/LICENSE
si_sr_gan_light-0.0.0.dist-info/METADATA
si_sr_gan_light-0.0.0.dist-info/WHEEL
si_sr_gan_light-0.0.0.dist-info/entry_points.txt
si_sr_gan_light-0.0.0.dist-info/top_level.txt
si_sr_gan_light-0.0.0.dist-info/RECORD
